LICENSE
README.md
docs/Makefile
docs/knitscript_lexer.py
docs/make.bat
docs/source/_static/custom.css
docs/source/_templates/module.rst_t
docs/source/_templates/package.rst_t
docs/source/acknowledgments.rst
docs/source/conf.py
docs/source/dependencies.rst
docs/source/index.rst
docs/source/installation.rst
docs/source/language_reference.rst
docs/source/machine_operations.rst
docs/source/quickstart.rst
docs/source/related_projects.rst
knit_script/__init__.py
knit_script/debugger/__init__.py
knit_script/debugger/debug_decorator.py
knit_script/debugger/debug_protocol.py
knit_script/debugger/enter_frame_decorator.py
knit_script/debugger/exit_frame_decorator.py
knit_script/debugger/knitscript_debugger.py
knit_script/debugger/knitscript_frame.py
knit_script/interpret_knit_script.py
knit_script/knit_script_exceptions/Knit_Script_Exception.py
knit_script/knit_script_exceptions/__init__.py
knit_script/knit_script_exceptions/gauge_sheet_exceptions.py
knit_script/knit_script_exceptions/parsing_exception.py
knit_script/knit_script_interpreter/Knit_Script_Interpreter.py
knit_script/knit_script_interpreter/Knit_Script_Parser.py
knit_script/knit_script_interpreter/Machine_Specification.py
knit_script/knit_script_interpreter/__init__.py
knit_script/knit_script_interpreter/expressions/Gauge_Expression.py
knit_script/knit_script_interpreter/expressions/Indexed_Expression.py
knit_script/knit_script_interpreter/expressions/__init__.py
knit_script/knit_script_interpreter/expressions/accessors.py
knit_script/knit_script_interpreter/expressions/carrier.py
knit_script/knit_script_interpreter/expressions/direction.py
knit_script/knit_script_interpreter/expressions/expressions.py
knit_script/knit_script_interpreter/expressions/formatted_string.py
knit_script/knit_script_interpreter/expressions/function_expressions.py
knit_script/knit_script_interpreter/expressions/instruction_expression.py
knit_script/knit_script_interpreter/expressions/list_expression.py
knit_script-0.2.0.dist-info/LICENSE
knit_script-0.2.0.dist-info/METADATA
knit_script-0.2.0.dist-info/WHEEL
knit_script-0.2.0.dist-info/RECORD
