Metadata-Version: 2.1
Name: knit-script
Version: 0.2.0
Summary: Knit Script is a domain specific programming language for writing v-bed knitting machine instructions. The language is loosely based on conventions from Python 3 but includes support for controlling a knitting machine. The code is interpreted into knitout which can then be processed into instructions for different types of knitting machines.
Home-page: https://mhofmann-khoury.github.io/knit_script/
License: MIT
Keywords: knit,machine knit,textile,Northeastern,ACT Lab,fabrication,knit script
Author: Megan Hofmann
Author-email: m.hofmann@northeastern.edu
Maintainer: Megan Hofmann
Maintainer-email: m.hofmann@northeastern.edu
Requires-Python: >=3.11,<3.14
Classifier: Development Status :: 2 - Pre-Alpha
Classifier: Intended Audience :: Developers
Classifier: Intended Audience :: Manufacturing
Classifier: Intended Audience :: Science/Research
Classifier: License :: OSI Approved :: MIT License
Classifier: Natural Language :: English
Classifier: Operating System :: OS Independent
Classifier: Programming Language :: Python :: 3
Classifier: Programming Language :: Python :: 3.11
Classifier: Programming Language :: Python :: 3.12
Classifier: Programming Language :: Python :: 3.13
Classifier: Topic :: Scientific/Engineering
Classifier: Typing :: Typed
Requires-Dist: importlib_resources (>=6.5)
Requires-Dist: knitout-interpreter (>=0.1.1)
Requires-Dist: parglare (>=0.19.0,<0.20.0)
Project-URL: Documentation, https://mhofmann-khoury.github.io/knit_script/
Project-URL: Repository, https://github.com/mhofmann-Khoury/knit_script
